stochastic_arrow/arrow.py
stochastic_arrow/__init__.py
stochastic_arrow/reference.py
stochastic_arrow/arrowhead.cpython-311-darwin.so
stochastic_arrow/math.py
stochastic_arrow-1.1.0.dist-info/RECORD
stochastic_arrow-1.1.0.dist-info/LICENSE
stochastic_arrow-1.1.0.dist-info/WHEEL
stochastic_arrow-1.1.0.dist-info/top_level.txt
stochastic_arrow-1.1.0.dist-info/METADATA
