Metadata-Version: 2.1
Name: stochastic-arrow
Version: 1.1.0
Home-page: https://github.com/CovertLab/arrow
Author: Ryan Spangler, John Mason, Jerry Morrison, Chris Skalnik, Travis Ahn-Horst, Sean Cheah
Author-email: ryan.spangler@gmail.com
License: MIT
Classifier: Development Status :: 3 - Alpha
Classifier: License :: OSI Approved :: MIT License
Classifier: Programming Language :: Python
Classifier: Programming Language :: Python :: 2.7
Classifier: Programming Language :: Python :: 3
Classifier: Topic :: Scientific/Engineering
License-File: LICENSE
Requires-Dist: numpy>=1.14
Requires-Dist: six
